{
  "node_id": "hellenic_iron_ore_2025-12-19_2025_12_19_mmi_daily_iron_ore_index_report_december_19_2025__root",
  "doc_id": "hellenic_iron_ore_2025-12-19_2025_12_19_mmi_daily_iron_ore_index_report_december_19_2025",
  "parent_id": null,
  "title": "MMI Daily Iron Ore Index Report December 19 2025",
  "section_path": [
    "MMI Daily Iron Ore Index Report December 19 2025"
  ],
  "section_path_text": "MMI Daily Iron Ore Index Report December 19 2025",
  "level": 0,
  "ordinal": 0,
  "summary": "Main\nin Chinese iron ore and steelmaking prices 19/12/2025\nDalian iron ore futures continued to fluctuate with a firm tone today. The main contract, I2605, ultimately closed at 780, up 0.52% from theprevious working day. Traders sold cargoes at prevailing market rates, whilst steel mills procured strictly on a needs basis.",
  "keywords": [
    "china",
    "iron_ore",
    "steel",
    "iron",
    "ore",
    "prices",
    "continued",
    "day.",
    "fines",
    "largely",
    "main",
    "mills"
  ],
  "page_start": null,
  "page_end": null,
  "token_count": 300,
  "source_path": "reports/hellenic/iron_ore/2025/2025-12-19_mmi-daily-iron-ore-index-report-december-19-2025.html",
  "source_url": "https://www.hellenicshippingnews.com/mmi-daily-iron-ore-index-report-december-19-2025",
  "children": [
    {
      "node_id": "hellenic_iron_ore_2025-12-19_2025_12_19_mmi_daily_iron_ore_index_report_december_19_2025__s01_main",
      "doc_id": "hellenic_iron_ore_2025-12-19_2025_12_19_mmi_daily_iron_ore_index_report_december_19_2025",
      "parent_id": "hellenic_iron_ore_2025-12-19_2025_12_19_mmi_daily_iron_ore_index_report_december_19_2025__root",
      "title": "Main",
      "section_path": [
        "Main"
      ],
      "section_path_text": "Main",
      "level": 1,
      "ordinal": 1,
      "summary": "in Chinese iron ore and steelmaking prices 19/12/2025\nDalian iron ore futures continued to fluctuate with a firm tone today. The main contract, I2605, ultimately closed at 780, up 0.52% from theprevious working day.",
      "keywords": [
        "china",
        "iron_ore",
        "steel",
        "iron",
        "ore",
        "prices",
        "continued",
        "day."
      ],
      "page_start": null,
      "page_end": null,
      "token_count": 298,
      "section_type": null,
      "children": []
    }
  ]
}