{
  "node_id": "baltic_container_2026-02-27_2026_02_27_container_report_week_9_container__root",
  "doc_id": "baltic_container_2026-02-27_2026_02_27_container_report_week_9_container",
  "parent_id": null,
  "title": "Container Report - Week 9",
  "section_path": [
    "Container Report - Week 9"
  ],
  "section_path_text": "Container Report - Week 9",
  "level": 0,
  "ordinal": 0,
  "summary": "Container\nLast Friday, the US Supreme Court ruled that President Trump did not have authority to create and impose last year's import tariffs as he did, effectively invalidating these tariffs. The American Government quickly imposed an alternative blanket 10pct tariff to all imports instead using a different legal statute. Chinese exports grew in 2025 despite a decline of exports to the United States; other countries took up the slack.",
  "keywords": [
    "container",
    "china",
    "europe",
    "last",
    "asia",
    "china/east",
    "ending",
    "friday",
    "any",
    "coast",
    "did",
    "down"
  ],
  "page_start": null,
  "page_end": null,
  "token_count": 14,
  "source_path": "reports/baltic/container/2026/2026-02-27_container-report-week-9_container.html",
  "source_url": null,
  "children": [
    {
      "node_id": "baltic_container_2026-02-27_2026_02_27_container_report_week_9_container__s01_main",
      "doc_id": "baltic_container_2026-02-27_2026_02_27_container_report_week_9_container",
      "parent_id": "baltic_container_2026-02-27_2026_02_27_container_report_week_9_container__root",
      "title": "Main",
      "section_path": [
        "Main"
      ],
      "section_path_text": "Main",
      "level": 1,
      "ordinal": 1,
      "summary": "27 Feb 2026\nContainer Report - Week 9",
      "keywords": [
        "container",
        "feb"
      ],
      "page_start": null,
      "page_end": null,
      "token_count": 12,
      "section_type": null,
      "children": []
    }
  ]
}