{
  "node_id": "baltic_tanker_2020-11-20_2020_11_20_tanker_report_week_47_tanker__root",
  "doc_id": "baltic_tanker_2020-11-20_2020_11_20_tanker_report_week_47_tanker",
  "parent_id": null,
  "title": "Tanker report - Week 47",
  "section_path": [
    "Tanker report - Week 47"
  ],
  "section_path_text": "Tanker report - Week 47",
  "level": 0,
  "ordinal": 0,
  "summary": "VLCC\nRates remain rooted across much of the sector. In the Middle East, 280,000mt to USG via the Cape/Cape routing continues to be assessed at W15 and 270,000mt to China is still hovering around WS26. In the Atlantic, rates for 260,000mt West Africa to China held around the WS29.5 level while 270,000mt US Gulf to China improved by about $90k to $4.6m.",
  "keywords": [
    "capesize",
    "vlcc",
    "suezmax",
    "aframax",
    "china",
    "brazil",
    "atlantic",
    "meg",
    "west_africa",
    "europe",
    "us_gulf",
    "japan"
  ],
  "page_start": null,
  "page_end": null,
  "token_count": 619,
  "source_path": "reports/baltic/tanker/2020/2020-11-20_tanker-report-week-47_tanker.html",
  "source_url": null,
  "children": [
    {
      "node_id": "baltic_tanker_2020-11-20_2020_11_20_tanker_report_week_47_tanker__s01_vlcc",
      "doc_id": "baltic_tanker_2020-11-20_2020_11_20_tanker_report_week_47_tanker",
      "parent_id": "baltic_tanker_2020-11-20_2020_11_20_tanker_report_week_47_tanker__root",
      "title": "VLCC",
      "section_path": [
        "VLCC"
      ],
      "section_path_text": "VLCC",
      "level": 1,
      "ordinal": 1,
      "summary": "Rates remain rooted across much of the sector. In the Middle East, 280,000mt to USG via the Cape/Cape routing continues to be assessed at W15 and 270,000mt to China is still hovering around WS26.",
      "keywords": [
        "capesize",
        "china",
        "atlantic",
        "west_africa",
        "us_gulf",
        "around",
        "africa",
        "area."
      ],
      "page_start": null,
      "page_end": null,
      "token_count": 116,
      "section_type": null,
      "children": []
    },
    {
      "node_id": "baltic_tanker_2020-11-20_2020_11_20_tanker_report_week_47_tanker__s02_suezmax",
      "doc_id": "baltic_tanker_2020-11-20_2020_11_20_tanker_report_week_47_tanker",
      "parent_id": "baltic_tanker_2020-11-20_2020_11_20_tanker_report_week_47_tanker__root",
      "title": "Suezmax",
      "section_path": [
        "Suezmax"
      ],
      "section_path_text": "Suezmax",
      "level": 1,
      "ordinal": 2,
      "summary": "Rates for 135,000mt Black Sea/Med rose 2.5-3 points to low WS50s, while owners in the 130,000mt Nigeria to UKContinent market were unable to stop rates sliding 2.5-3 points to WS36.5/37 level. In the Middle East market, rates slipped two points to WS20 for 140,000mt Basrah/Med.",
      "keywords": [
        "europe",
        "points",
        "basrah/med.",
        "black",
        "east",
        "level.",
        "low",
        "middle"
      ],
      "page_start": null,
      "page_end": null,
      "token_count": 86,
      "section_type": null,
      "children": []
    },
    {
      "node_id": "baltic_tanker_2020-11-20_2020_11_20_tanker_report_week_47_tanker__s03_aframax",
      "doc_id": "baltic_tanker_2020-11-20_2020_11_20_tanker_report_week_47_tanker",
      "parent_id": "baltic_tanker_2020-11-20_2020_11_20_tanker_report_week_47_tanker__root",
      "title": "Aframax",
      "section_path": [
        "Aframax"
      ],
      "section_path_text": "Aframax",
      "level": 1,
      "ordinal": 3,
      "summary": "In the 80,000mt Ceyhan/Lavera market, rates have eased to be last assessed at W61. However, a couple of fixtures overnight have been reported at WS57.5 - down 7.5 points week-on-week.",
      "keywords": [
        "atlantic",
        "europe",
        "points",
        "continued",
        "able",
        "around",
        "assessed",
        "baltic/ukc"
      ],
      "page_start": null,
      "page_end": null,
      "token_count": 158,
      "section_type": null,
      "children": []
    },
    {
      "node_id": "baltic_tanker_2020-11-20_2020_11_20_tanker_report_week_47_tanker__s04_clean",
      "doc_id": "baltic_tanker_2020-11-20_2020_11_20_tanker_report_week_47_tanker",
      "parent_id": "baltic_tanker_2020-11-20_2020_11_20_tanker_report_week_47_tanker__root",
      "title": "Clean",
      "section_path": [
        "Clean"
      ],
      "section_path_text": "Clean",
      "level": 1,
      "ordinal": 4,
      "summary": "In the Middle East Gulf/Japan trade, owners were able to maintain the firming trend of the previous week and rates gained around five to six points for 75,000mt to sit now in the low WS80s. It was a similar story in the LR1 trade with rates for 55,000mt to Japan now up in the WS80 region, representing a four-point improvement from a week ago.",
      "keywords": [
        "brazil",
        "meg",
        "west_africa",
        "europe",
        "us_gulf",
        "japan",
        "trade",
        "now"
      ],
      "page_start": null,
      "page_end": null,
      "token_count": 246,
      "section_type": null,
      "children": []
    }
  ]
}